[
  {
    "id": "beef",
    "originalRaw": "beef",
    "count": 5
  },
  {
    "id": "nutmeg",
    "originalRaw": "ground nutmeg",
    "count": 5
  },
  {
    "id": "salt_and_pepper",
    "originalRaw": "salt and ground pepper",
    "count": 4
  },
  {
    "id": "sundried_tomatoes",
    "originalRaw": "sundried tomatoes",
    "count": 3
  },
  {
    "id": "lamb",
    "originalRaw": "lamb",
    "count": 3
  },
  {
    "id": "cloves",
    "originalRaw": "ground cloves",
    "count": 3
  },
  {
    "id": "allspice",
    "originalRaw": "ground allspice",
    "count": 2
  },
  {
    "id": "nonfat_greek_yogurt",
    "originalRaw": "nonfat greek yogurt",
    "count": 2
  },
  {
    "id": "salt_pepper",
    "originalRaw": "salt& pepper",
    "count": 2
  },
  {
    "id": "sharp_cheddar_cheese",
    "originalRaw": "extra sharp cheddar cheese",
    "count": 2
  }
]